{".class": "MypyFile", "_fullname": "PyQRCodeReaderImage", "is_partial_stub_package": false, "is_stub": false, "names": {".class": "SymbolTable", "QtCore": {".class": "SymbolTableNode", "kind": "Gdef", "node": {".class": "Var", "flags": ["is_suppressed_import", "is_ready"], "fullname": "PyQRCodeReaderImage.QtCore", "name": "QtCore", "type": {".class": "AnyType", "missing_import_name": "PyQRCodeReaderImage.QtCore", "source_any": null, "type_of_any": 3}}}, "QtGui": {".class": "SymbolTableNode", "kind": "Gdef", "node": {".class": "Var", "flags": ["is_suppressed_import", "is_ready"], "fullname": "PyQRCodeReaderImage.QtGui", "name": "QtGui", "type": {".class": "AnyType", "missing_import_name": "PyQRCodeReaderImage.QtGui", "source_any": null, "type_of_any": 3}}}, "QtWidgets": {".class": "SymbolTableNode", "kind": "Gdef", "node": {".class": "Var", "flags": ["is_suppressed_import", "is_ready"], "fullname": "PyQRCodeReaderImage.QtWidgets", "name": "QtWidgets", "type": {".class": "AnyType", "missing_import_name": "PyQRCodeReaderImage.QtWidgets", "source_any": null, "type_of_any": 3}}}, "Ui_readFromImageWindow": {".class": "SymbolTableNode", "kind": "Gdef", "node": {".class": "TypeInfo", "_promote": null, "abstract_attributes": [], "bases": ["builtins.object"], "declared_metaclass": null, "defn": {".class": "ClassDef", "fullname": "PyQRCodeReaderImage.Ui_readFromImageWindow", "name": "Ui_readFromImageWindow", "type_vars": []}, "flags": [], "fullname": "PyQRCodeReaderImage.Ui_readFromImageWindow", "metaclass_type": null, "metadata": {}, "module_name": "PyQRCodeReaderImage", "mro": ["PyQRCodeReaderImage.Ui_readFromImageWindow", "builtins.object"], "names": {".class": "SymbolTable", "browse": {".class": "SymbolTableNode", "implicit": true, "kind": "Mdef", "node": {".class": "Var", "flags": [], "fullname": "PyQRCodeReaderImage.Ui_readFromImageWindow.browse", "name": "browse", "type": {".class": "AnyType", "missing_import_name": null, "source_any": null, "type_of_any": 1}}}, "browseFileName": {".class": "SymbolTableNode", "kind": "Mdef", "node": {".class": "FuncDef", "arg_kinds": [0], "arg_names": ["self"], "flags": [], "fullname": "PyQRCodeReaderImage.Ui_readFromImageWindow.browseFileName", "name": "browseFileName", "type": null}}, "centralwidget": {".class": "SymbolTableNode", "implicit": true, "kind": "Mdef", "node": {".class": "Var", "flags": [], "fullname": "PyQRCodeReaderImage.Ui_readFromImageWindow.centralwidget", "name": "centralwidget", "type": {".class": "AnyType", "missing_import_name": null, "source_any": null, "type_of_any": 1}}}, "dataLabel": {".class": "SymbolTableNode", "implicit": true, "kind": "Mdef", "node": {".class": "Var", "flags": [], "fullname": "PyQRCodeReaderImage.Ui_readFromImageWindow.dataLabel", "name": "dataLabel", "type": {".class": "AnyType", "missing_import_name": null, "source_any": null, "type_of_any": 1}}}, "dataRead": {".class": "SymbolTableNode", "implicit": true, "kind": "Mdef", "node": {".class": "Var", "flags": [], "fullname": "PyQRCodeReaderImage.Ui_readFromImageWindow.dataRead", "name": "dataRead", "type": {".class": "AnyType", "missing_import_name": null, "source_any": null, "type_of_any": 1}}}, "menubar": {".class": "SymbolTableNode", "implicit": true, "kind": "Mdef", "node": {".class": "Var", "flags": [], "fullname": "PyQRCodeReaderImage.Ui_readFromImageWindow.menubar", "name": "menubar", "type": {".class": "AnyType", "missing_import_name": null, "source_any": null, "type_of_any": 1}}}, "opText": {".class": "SymbolTableNode", "implicit": true, "kind": "Mdef", "node": {".class": "Var", "flags": [], "fullname": "PyQRCodeReaderImage.Ui_readFromImageWindow.opText", "name": "opText", "type": {".class": "AnyType", "missing_import_name": null, "source_any": null, "type_of_any": 1}}}, "openLabel": {".class": "SymbolTableNode", "implicit": true, "kind": "Mdef", "node": {".class": "Var", "flags": [], "fullname": "PyQRCodeReaderImage.Ui_readFromImageWindow.openLabel", "name": "openLabel", "type": {".class": "AnyType", "missing_import_name": null, "source_any": null, "type_of_any": 1}}}, "readImage": {".class": "SymbolTableNode", "implicit": true, "kind": "Mdef", "node": {".class": "Var", "flags": [], "fullname": "PyQRCodeReaderImage.Ui_readFromImageWindow.readImage", "name": "readImage", "type": {".class": "AnyType", "missing_import_name": null, "source_any": null, "type_of_any": 1}}}, "readQRCode": {".class": "SymbolTableNode", "kind": "Mdef", "node": {".class": "FuncDef", "arg_kinds": [0], "arg_names": ["self"], "flags": [], "fullname": "PyQRCodeReaderImage.Ui_readFromImageWindow.readQRCode", "name": "readQRCode", "type": null}}, "retranslateUi": {".class": "SymbolTableNode", "kind": "Mdef", "node": {".class": "FuncDef", "arg_kinds": [0, 0], "arg_names": ["self", "readFromImageWindow"], "flags": [], "fullname": "PyQRCodeReaderImage.Ui_readFromImageWindow.retranslateUi", "name": "retranslateUi", "type": null}}, "saveText": {".class": "SymbolTableNode", "kind": "Mdef", "node": {".class": "FuncDef", "arg_kinds": [0], "arg_names": ["self"], "flags": [], "fullname": "PyQRCodeReaderImage.Ui_readFromImageWindow.saveText", "name": "saveText", "type": null}}, "saveasText": {".class": "SymbolTableNode", "implicit": true, "kind": "Mdef", "node": {".class": "Var", "flags": [], "fullname": "PyQRCodeReaderImage.Ui_readFromImageWindow.saveasText", "name": "saveasText", "type": {".class": "AnyType", "missing_import_name": null, "source_any": null, "type_of_any": 1}}}, "setupUi": {".class": "SymbolTableNode", "kind": "Mdef", "node": {".class": "FuncDef", "arg_kinds": [0, 0], "arg_names": ["self", "readFromImageWindow"], "flags": [], "fullname": "PyQRCodeReaderImage.Ui_readFromImageWindow.setupUi", "name": "setupUi", "type": null}}, "statusbar": {".class": "SymbolTableNode", "implicit": true, "kind": "Mdef", "node": {".class": "Var", "flags": [], "fullname": "PyQRCodeReaderImage.Ui_readFromImageWindow.statusbar", "name": "statusbar", "type": {".class": "AnyType", "missing_import_name": null, "source_any": null, "type_of_any": 1}}}, "titleReaderImage": {".class": "SymbolTableNode", "implicit": true, "kind": "Mdef", "node": {".class": "Var", "flags": [], "fullname": "PyQRCodeReaderImage.Ui_readFromImageWindow.titleReaderImage", "name": "titleReaderImage", "type": {".class": "AnyType", "missing_import_name": null, "source_any": null, "type_of_any": 1}}}}, "tuple_type": null, "type_vars": [], "typeddict_type": null}}, "__doc__": {".class": "SymbolTableNode", "kind": "Gdef", "node": {".class": "Var", "flags": ["is_ready"], "fullname": "PyQRCodeReaderImage.__doc__", "name": "__doc__", "type": "builtins.str"}}, "__file__": {".class": "SymbolTableNode", "kind": "Gdef", "node": {".class": "Var", "flags": ["is_ready"], "fullname": "PyQRCodeReaderImage.__file__", "name": "__file__", "type": "builtins.str"}}, "__name__": {".class": "SymbolTableNode", "kind": "Gdef", "node": {".class": "Var", "flags": ["is_ready"], "fullname": "PyQRCodeReaderImage.__name__", "name": "__name__", "type": "builtins.str"}}, "__package__": {".class": "SymbolTableNode", "kind": "Gdef", "node": {".class": "Var", "flags": ["is_ready"], "fullname": "PyQRCodeReaderImage.__package__", "name": "__package__", "type": "builtins.str"}}, "app": {".class": "SymbolTableNode", "kind": "Gdef", "node": {".class": "Var", "flags": [], "fullname": "PyQRCodeReaderImage.app", "name": "app", "type": {".class": "AnyType", "missing_import_name": "PyQRCodeReaderImage.QtWidgets", "source_any": {".class": "AnyType", "missing_import_name": "PyQRCodeReaderImage.QtWidgets", "source_any": null, "type_of_any": 3}, "type_of_any": 7}}}, "cv2": {".class": "SymbolTableNode", "kind": "Gdef", "node": {".class": "Var", "flags": ["is_suppressed_import", "is_ready"], "fullname": "PyQRCodeReaderImage.cv2", "name": "cv2", "type": {".class": "AnyType", "missing_import_name": "PyQRCodeReaderImage.cv2", "source_any": null, "type_of_any": 3}}}, "decode": {".class": "SymbolTableNode", "kind": "Gdef", "node": {".class": "Var", "flags": ["is_suppressed_import", "is_ready"], "fullname": "PyQRCodeReaderImage.decode", "name": "decode", "type": {".class": "AnyType", "missing_import_name": "PyQRCodeReaderImage.decode", "source_any": null, "type_of_any": 3}}}, "logo_rc": {".class": "SymbolTableNode", "cross_ref": "logo_rc", "kind": "Gdef"}, "readFromImageWindow": {".class": "SymbolTableNode", "kind": "Gdef", "node": {".class": "Var", "flags": [], "fullname": "PyQRCodeReaderImage.readFromImageWindow", "name": "readFromImageWindow", "type": {".class": "AnyType", "missing_import_name": "PyQRCodeReaderImage.QtWidgets", "source_any": {".class": "AnyType", "missing_import_name": "PyQRCodeReaderImage.QtWidgets", "source_any": null, "type_of_any": 3}, "type_of_any": 7}}}, "sys": {".class": "SymbolTableNode", "cross_ref": "sys", "kind": "Gdef"}, "ui": {".class": "SymbolTableNode", "kind": "Gdef", "node": {".class": "Var", "flags": [], "fullname": "PyQRCodeReaderImage.ui", "name": "ui", "type": "PyQRCodeReaderImage.Ui_readFromImageWindow"}}}, "path": "e:\\Works\\Programming\\Projects\\QRCode version 1.1\\PyQRCode version 1.1\\PyQRCodeReaderImage.py"}